mlrq/__init__.py
mlrq/mlrq.py
mlrq-0.1.5.dist-info/LICENSE
mlrq-0.1.5.dist-info/METADATA
mlrq-0.1.5.dist-info/WHEEL
mlrq-0.1.5.dist-info/RECORD
