Metadata-Version: 2.1
Name: mlrq
Version: 0.1.5
Summary: 
Author: Filippos Christianos
Author-email: f.christianos@ed.ac.uk
Requires-Python: >=3.10,<4.0
Classifier: Programming Language :: Python :: 3
Classifier: Programming Language :: Python :: 3.10
Classifier: Programming Language :: Python :: 3.11
Classifier: Programming Language :: Python :: 3.12
Requires-Dist: redis (>=5.0.1,<6.0.0)
